auth0_fastapi/__init__.py
auth0_fastapi/auth0_jwt_bearer_token_validator.py
auth0_fastapi/exceptions.py
auth0_fastapi-0.0.3.dist-info/LICENSE
auth0_fastapi-0.0.3.dist-info/METADATA
auth0_fastapi-0.0.3.dist-info/WHEEL
auth0_fastapi-0.0.3.dist-info/RECORD
