Metadata-Version: 2.1
Name: auth0_fastapi
Version: 0.0.3
Summary: A must have if you are using Auth0 with FastAPI
Author: Juan Cruz Martinez
Author-email: bajcmartinez@gmail.com
Requires-Python: >=3.11
Classifier: Programming Language :: Python :: 3
Classifier: Programming Language :: Python :: 3.11
Classifier: Programming Language :: Python :: 3.12
Requires-Dist: cryptography (>=41.0.7,<42.0.0)
Requires-Dist: fastapi (>=0.105.0)
Requires-Dist: pyjwt (>=2.8.0,<3.0.0)
